LICENSE
MANIFEST.in
README.rst
setup.py
adhara/__init__.py
adhara/admin.py
adhara/apps.py
adhara/decorators.py
adhara/exceptions.py
adhara/meta.py
adhara/middleware.py
adhara/request.py
adhara/response.py
adhara/response_utils.py
adhara/restview.py
adhara/session.py
adhara/tests.py
adhara/tests_utils.py
adhara/thread_local.py
adhara/urls.py
adhara/utilities.py
adhara/views.py
adhara/events/__init__.py
adhara/events/base.py
adhara/events/firebase.py
adhara/events/handler.py
adhara/models/__init__.py
adhara/models/base_models.py
adhara/models/event_models.py
adhara/templates/adhara/head.html
django_adhara.egg-info/PKG-INFO
django_adhara.egg-info/SOURCES.txt
django_adhara.egg-info/dependency_links.txt
django_adhara.egg-info/requires.txt
django_adhara.egg-info/top_level.txt
docs/settings.txt